{
  "$id": "1",
  "DeviceName": "NSW3BA0064",
  "DeviceMode": "1000Hz64",
  "RecordChannelSettingGroup": "10-20",
  "RecordMontageName": "MI26",
  "RecordTrendName": "",
  "RecordProtocolName": "Raw Signal",
  "RecordEEGCapName": "EEGCap64-V3.0",
  "PatientGUID": "a6fc211d-a6c4-495d-a4e6-83415d7d995a",
  "PatientID": "a02",
  "ExamGUID": "dc155788-f785-43f2-bdb8-623735ce55de",
  "PatientName": "zhangyajun",
  "BirthDate": "1990-01-01T00:00:00",
  "Gender": 0,
  "National": "",
  "Professional": "",
  "Organization": "",
  "Address": "",
  "Contact": "",
  "PatientNote": "",
  "ExamTime": "2018-07-14T09:38:45",
  "AdmissionID": "",
  "BedNumber": "",
  "ExamItem": "",
  "ExamID": "E201807140938436904",
  "FirstDiagnosed": "",
  "Pathography": "",
  "ExamNote": "",
  "RequestDepartment": "",
  "RequestDoctor": "",
  "ExamDepartment": "",
  "ExamDoctor": "",
  "DiagnosisDoctor": "",
  "ExamResult": "",
  "ImpedanceData": {
    "$id": "2",
    "Item1": [
      "Cz",
      "CP1",
      "C4",
      "Pz",
      "O1",
      "Fp1",
      "CP6",
      "O2",
      "CP2",
      "P8",
      "C3",
      "P7",
      "Fp2",
      "F8",
      "CP5",
      "F7",
      "HEOL",
      "FC5",
      "HEOR",
      "P4",
      "T7",
      "F3",
      "T8",
      "FC2",
      "PO4",
      "FC6",
      "P3",
      "PO3",
      "Oz",
      "F4",
      "FC1",
      "Fz",
      "FC4",
      "Fpz",
      "P6",
      "FCz",
      "C6",
      "POz",
      "F6",
      "PO6",
      "PO8",
      "C2",
      "TP8",
      "F2",
      "FT8",
      "AF4",
      "AF8",
      "CP4",
      "AF7",
      "CP3",
      "FT7",
      "AF3",
      "TP7",
      "F1",
      "PO7",
      "C1",
      "F5",
      "PO5",
      "C5",
      "ECG",
      "P5",
      "VEOL",
      "FC3",
      "VEOU"
    ],
    "Item2": [
      7.002537,
      6.77281952,
      8.8274,
      21125.125,
      21068.56,
      20953.1855,
      13.4632645,
      20990.8633,
      10.8505745,
      21137.5586,
      3.67979,
      21040.2051,
      20972.1328,
      20965.9746,
      9.890676,
      20977.2539,
      20950.7383,
      9.195287,
      20875.5313,
      21143.0938,
      9.070474,
      20792.1719,
      12.5128765,
      7.208045,
      21095.3477,
      7.210021,
      21135.4219,
      21125.5254,
      21015.5977,
      21093.91,
      15.4551373,
      21111.9941,
      10.526206,
      20835.2148,
      21103.1484,
      8.722034,
      17.6659565,
      21123.2188,
      21095.78,
      21097.9063,
      21145.9043,
      7.191435,
      14.6289673,
      20991.86,
      14.2875919,
      21062.1016,
      21008.41,
      11.8267365,
      20784.1973,
      15.9735279,
      18.1088829,
      20816.9844,
      17.0238419,
      20851.9023,
      21141.0215,
      9.267292,
      20842.5371,
      21139.52,
      9.96133,
      20932.3418,
      21080.5254,
      20882.31,
      13.605772,
      1712.96143
    ]
  },
  "ImpedanceOnline": false,
  "DataFileInformations": [
    {
      "$id": "3",
      "BeginTimeStamp": 0,
      "DataLength": 0
    }
  ],
  "DigitalMinimum": -8388608,
  "DigitalMaximum": 8388607,
  "PhysicalMinimum": -375000.0,
  "PhysicalMaximum": 375000.0,
  "SampleRate": 1000
}